obscure/__init__.py
obscure/__main__.py
obscure/encoder.py
obscure/feistel.py
obscure-1.0.4.dist-info/licenses/LICENSE
obscure-1.0.4.dist-info/METADATA
obscure-1.0.4.dist-info/WHEEL
obscure-1.0.4.dist-info/top_level.txt
obscure-1.0.4.dist-info/RECORD
