Metadata-Version: 2.4
Name: obscure
Version: 1.0.4
Summary: Create reversible transformations to obscure sequential ID numbers.
Author-email: Clinton James <clinton+obscure@jidn.com>
License-Expression: MIT
Project-URL: Homepage, https://github.com/jidn/obscure
Project-URL: Documentation, https://github.com/jidn/obscure#readme
Project-URL: Issues, https://github.com/jidn/obscure/issues
Project-URL: Source, https://github.com/jidn/obscure
Keywords: obfuscate,feistel,ids
Classifier: Development Status :: 5 - Production/Stable
Classifier: Intended Audience :: Developers
Classifier: Programming Language :: Python :: 3
Classifier: Programming Language :: Python :: 3 :: Only
Classifier: Programming Language :: Python :: 3.9
Classifier: Programming Language :: Python :: 3.10
Classifier: Programming Language :: Python :: 3.11
Classifier: Programming Language :: Python :: 3.12
Classifier: Programming Language :: Python :: 3.13
Classifier: Operating System :: OS Independent
Requires-Python: >=3.9
License-File: LICENSE
Dynamic: license-file
